pydebugstring/__init__.py
pydebugstring/output.py
pydebugstring/outputdebugstringhandler.py
pydebugstring-1.0.0.1.dist-info/WHEEL
pydebugstring-1.0.0.1.dist-info/METADATA
pydebugstring-1.0.0.1.dist-info/RECORD
