Metadata-Version: 2.1
Name: pydebugstring
Version: 1.0.0.1
Summary: function to write python obects to OutputDebugString on windows
Home-page: https://github.com/dougransom/pydebugstring
Author: Doug Ransom
Author-email: doug@ransom.vip
Requires-Python: >=3.0
Classifier: Intended Audience :: Developers
Classifier: License :: OSI Approved :: BSD License
Classifier: Programming Language :: Python :: 3
Classifier: Topic :: Software Development :: Libraries :: Python Modules
